marksfuncs/__init__.py
marksfuncs/functions.py
marksfuncs-0.2.dist-info/LICENSE.txt
marksfuncs-0.2.dist-info/METADATA
marksfuncs-0.2.dist-info/WHEEL
marksfuncs-0.2.dist-info/top_level.txt
marksfuncs-0.2.dist-info/RECORD
