Metadata-Version: 2.1
Name: marksfuncs
Version: 0.2
Summary: Graph many mathematical functions
Home-page: https://github.com/marc1fino/marksfuncs
Author: mark. (Marc Pérez)
Author-email: <marcperezcarrasco2010@gmail.com>
License: MIT
Keywords: python,maths,graphics,functions,xy,mathematical functions
Classifier: Intended Audience :: Developers
Classifier: Programming Language :: Python :: 3
Classifier: Operating System :: Unix
Classifier: Operating System :: MacOS :: MacOS X
Classifier: Operating System :: Microsoft :: Windows
License-File: LICENSE.txt
Requires-Dist: numpy
Requires-Dist: matplotlib
Requires-Dist: scipy
